Workbook

Sheet Dashboard
A1: Casa Yano - Loan Evaluator
A2: Identify optimal loan structure and quantify value of lender concessions
A3: Built from 2026-07-07 pro forma. Blue cells are inputs - adjust to test scenarios.
A5: PRO FORMA INPUTS
A6: Projected 2026 NOI (after fixed costs) | B6: 347853
A7: NOI scenario adjustment | B7: 1 | E7: (0% = current pro forma; +10% = optimistic case)
A8: Adjusted NOI | B8: =B6*B7
A10: PROPERTY ASSUMPTIONS
A11: Total Basis (per QBO) | B11: 4200000
A12: Existing Debt (private loan, 9.5% IO) | B12: 1500000
A13: Existing Equity | B13: =Dashboard!$B$11-Dashboard!$B$12
A15: VALUATION & UNDERWRITING ASSUMPTIONS
A16: Cap Rate (for valuation - center of sensitivity) | B16: 0.06
A17: Implied Property Value | B17: =Dashboard!$B$8/Dashboard!$B$16
A19: LENDER SCENARIOS (CURRENT TERMS)
A20: Lender / Option | B20: Loan Amount | C20: Notes | D20: Rate | E20: Amort
A21: Ben / MBT - Option 1 | B21: 2300000 | C21: 1.35x DSCR / 55% LTV / 0.50% fee / Day-1 amort | D21: 0.0625 | E21: 25
A22: Ben / MBT - Option 2 (with earn-out) | B22: 2800000 | C22: 1.35x DSCR / 60% LTV / 0.75% fee / 12mo IO | D22: 0.064 | E22: 25
A23: ServisFirst (current indicative) | C23: 1.50x DSCR / 75% LTV / Earn-out 2-phase TBD | D23: 0.065 | E23: 20
A26: DECISION SUPPORT - SEE OTHER TABS FOR DETAIL
A27: Tab 2: Valuation Sensitivity | B27: Property value at various NOI / cap rate combinations
A28: Tab 3: Max Loan Capacity | B28: Maximum loan by LTV constraint, DSCR constraint, and binding factor
A29: Tab 4: Lender Comparison | B29: Side-by-side analysis of all three lender scenarios
A30: Tab 5: Concession Levers | B30: How much each lender concession is worth in additional proceeds

Sheet Valuation Sensitivity
A1: Property Valuation Sensitivity
A2: Implied property value at various NOI scenarios and cap rates
A3: Formula: Property Value = NOI / Cap Rate
A5: NOI Scenario | B5: 0.045 | C5: 0.05 | D5: 0.055 | E5: 0.06 | F5: 0.065 | G5: 0.07 | H5: 0.075
A6: Conservative (-10%) | B6: =Dashboard!$B$6*0.9/0.045 | C6: =Dashboard!$B$6*0.9/0.05 | D6: =Dashboard!$B$6*0.9/0.055 | E6: =Dashboard!$B$6*0.9/0.06 | F6: =Dashboard!$B$6*0.9/0.065 | G6: =Dashboard!$B$6*0.9/0.07 | H6: =Dashboard!$B$6*0.9/0.075
A7: Conservative (-5%) | B7: =Dashboard!$B$6*0.95/0.045 | C7: =Dashboard!$B$6*0.95/0.05 | D7: =Dashboard!$B$6*0.95/0.055 | E7: =Dashboard!$B$6*0.95/0.06 | F7: =Dashboard!$B$6*0.95/0.065 | G7: =Dashboard!$B$6*0.95/0.07 | H7: =Dashboard!$B$6*0.95/0.075
A8: Current Pro Forma | B8: =Dashboard!$B$6*1.0/0.045 | C8: =Dashboard!$B$6*1.0/0.05 | D8: =Dashboard!$B$6*1.0/0.055 | E8: =Dashboard!$B$6*1.0/0.06 | F8: =Dashboard!$B$6*1.0/0.065 | G8: =Dashboard!$B$6*1.0/0.07 | H8: =Dashboard!$B$6*1.0/0.075
A9: Modest Beat (+5%) | B9: =Dashboard!$B$6*1.05/0.045 | C9: =Dashboard!$B$6*1.05/0.05 | D9: =Dashboard!$B$6*1.05/0.055 | E9: =Dashboard!$B$6*1.05/0.06 | F9: =Dashboard!$B$6*1.05/0.065 | G9: =Dashboard!$B$6*1.05/0.07 | H9: =Dashboard!$B$6*1.05/0.075
A10: Strong Beat (+10%) | B10: =Dashboard!$B$6*1.1/0.045 | C10: =Dashboard!$B$6*1.1/0.05 | D10: =Dashboard!$B$6*1.1/0.055 | E10: =Dashboard!$B$6*1.1/0.06 | F10: =Dashboard!$B$6*1.1/0.065 | G10: =Dashboard!$B$6*1.1/0.07 | H10: =Dashboard!$B$6*1.1/0.075
A11: Bull Case (+15%) | B11: =Dashboard!$B$6*1.15/0.045 | C11: =Dashboard!$B$6*1.15/0.05 | D11: =Dashboard!$B$6*1.15/0.055 | E11: =Dashboard!$B$6*1.15/0.06 | F11: =Dashboard!$B$6*1.15/0.065 | G11: =Dashboard!$B$6*1.15/0.07 | H11: =Dashboard!$B$6*1.15/0.075
A12: Bull Case (+20%) | B12: =Dashboard!$B$6*1.2/0.045 | C12: =Dashboard!$B$6*1.2/0.05 | D12: =Dashboard!$B$6*1.2/0.055 | E12: =Dashboard!$B$6*1.2/0.06 | F12: =Dashboard!$B$6*1.2/0.065 | G12: =Dashboard!$B$6*1.2/0.07 | H12: =Dashboard!$B$6*1.2/0.075
A15: NOTES
A16: - 6.0% cap rate is reasonable for SB STR with strong location and renovation
A17: - Lender appraisers typically use 5.5% - 6.5% range for SB lodging assets
A18: - Higher cap rate = more conservative valuation (lower value)

Sheet Max Loan Capacity
A1: Maximum Loan Capacity Analysis
A2: Max loan by LTV constraint, DSCR constraint, and binding factor (lesser of two)
A4: MAX LOAN BY LTV (using current pro forma NOI)
A5: Cap Rate Used | B5: 50% LTV | C5: 55% LTV | D5: 60% LTV | E5: 65% LTV | F5: 70% LTV | G5: 75% LTV
A6: 5.5% cap | B6: =Dashboard!$B$8/0.055*0.5 | C6: =Dashboard!$B$8/0.055*0.55 | D6: =Dashboard!$B$8/0.055*0.6 | E6: =Dashboard!$B$8/0.055*0.65 | F6: =Dashboard!$B$8/0.055*0.7 | G6: =Dashboard!$B$8/0.055*0.75
A7: 6.0% cap | B7: =Dashboard!$B$8/0.06*0.5 | C7: =Dashboard!$B$8/0.06*0.55 | D7: =Dashboard!$B$8/0.06*0.6 | E7: =Dashboard!$B$8/0.06*0.65 | F7: =Dashboard!$B$8/0.06*0.7 | G7: =Dashboard!$B$8/0.06*0.75
A8: 6.5% cap | B8: =Dashboard!$B$8/0.065*0.5 | C8: =Dashboard!$B$8/0.065*0.55 | D8: =Dashboard!$B$8/0.065*0.6 | E8: =Dashboard!$B$8/0.065*0.65 | F8: =Dashboard!$B$8/0.065*0.7 | G8: =Dashboard!$B$8/0.065*0.75
A11: MAX LOAN BY DSCR (using current pro forma NOI)
A12: Rate / Amort | B12: 1.20x DSCR | C12: 1.25x DSCR | D12: 1.35x DSCR | E12: 1.50x DSCR
A13: 6.25% / 25-yr | B13: =Dashboard!$B$8/1.2/0.07916032539780565 | C13: =Dashboard!$B$8/1.25/0.07916032539780565 | D13: =Dashboard!$B$8/1.35/0.07916032539780565 | E13: =Dashboard!$B$8/1.5/0.07916032539780565
A14: 6.40% / 25-yr | B14: =Dashboard!$B$8/1.2/0.0802766252022255 | C14: =Dashboard!$B$8/1.25/0.0802766252022255 | D14: =Dashboard!$B$8/1.35/0.0802766252022255 | E14: =Dashboard!$B$8/1.5/0.0802766252022255
A15: 6.25% / 30-yr | B15: =Dashboard!$B$8/1.2/0.07388606405116734 | C15: =Dashboard!$B$8/1.25/0.07388606405116734 | D15: =Dashboard!$B$8/1.35/0.07388606405116734 | E15: =Dashboard!$B$8/1.5/0.07388606405116734
A16: 6.50% / 20-yr | B16: =Dashboard!$B$8/1.2/0.089468776261812 | C16: =Dashboard!$B$8/1.25/0.089468776261812 | D16: =Dashboard!$B$8/1.35/0.089468776261812 | E16: =Dashboard!$B$8/1.5/0.089468776261812
A17: 6.50% / 25-yr | B17: =Dashboard!$B$8/1.2/0.08102485936171701 | C17: =Dashboard!$B$8/1.25/0.08102485936171701 | D17: =Dashboard!$B$8/1.35/0.08102485936171701 | E17: =Dashboard!$B$8/1.5/0.08102485936171701
A18: 6.50% / 30-yr | B18: =Dashboard!$B$8/1.2/0.07584816281915584 | C18: =Dashboard!$B$8/1.25/0.07584816281915584 | D18: =Dashboard!$B$8/1.35/0.07584816281915584 | E18: =Dashboard!$B$8/1.5/0.07584816281915584
A19: 7.00% / 25-yr | B19: =Dashboard!$B$8/1.2/0.0848135036730109 | C19: =Dashboard!$B$8/1.25/0.0848135036730109 | D19: =Dashboard!$B$8/1.35/0.0848135036730109 | E19: =Dashboard!$B$8/1.5/0.0848135036730109
A20: 7.50% / 25-yr | B20: =Dashboard!$B$8/1.2/0.08867894133569468 | C20: =Dashboard!$B$8/1.25/0.08867894133569468 | D20: =Dashboard!$B$8/1.35/0.08867894133569468 | E20: =Dashboard!$B$8/1.5/0.08867894133569468
A23: BINDING CONSTRAINT (lesser of LTV or DSCR max)
A24: Selected lender scenarios applied to current pro forma:
A25: Lender Scenario | B25: LTV Max | C25: DSCR Max | D25: Binding | E25: Constraint
A26: Ben Option 1: 55% LTV / 1.35x / 6.25% / 25-yr | B26: =Dashboard!$B$8/0.06*0.55 | C26: =Dashboard!$B$8/1.35/0.07916032539780565 | D26: =MIN(B26,C26) | E26: =IF(B26<C26,"LTV","DSCR")
A27: Ben Option 2: 60% LTV / 1.35x / 6.40% / 25-yr | B27: =Dashboard!$B$8/0.06*0.6 | C27: =Dashboard!$B$8/1.35/0.0802766252022255 | D27: =MIN(B27,C27) | E27: =IF(B27<C27,"LTV","DSCR")
A28: ServisFirst: 75% LTV / 1.50x / 6.50% / 20-yr | B28: =Dashboard!$B$8/0.06*0.75 | C28: =Dashboard!$B$8/1.5/0.089468776261812 | D28: =MIN(B28,C28) | E28: =IF(B28<C28,"LTV","DSCR")
A29: ServisFirst neg: 75% LTV / 1.35x / 6.50% / 25-yr | B29: =Dashboard!$B$8/0.06*0.75 | C29: =Dashboard!$B$8/1.35/0.08102485936171701 | D29: =MIN(B29,C29) | E29: =IF(B29<C29,"LTV","DSCR")
A31: Note: LTV calc assumes 6.0% cap rate. Adjust on Dashboard tab to test different cap rates.

Sheet Lender Comparison
A1: Lender Comparison
A2: Side-by-side at current terms with cash flow and return analysis
B4: Ben Opt 1 | C4: Ben Opt 2 | D4: ServisFirst (current) | E4: ServisFirst (negotiated)
A5: LOAN TERMS
A6: Loan Amount | B6: 2300000 | C6: 2800000 | D6: 2591988.1 | E6: 3255025.6
A7: Interest Rate | B7: 0.0625 | C7: 0.064 | D7: 0.065 | E7: 0.0625
A8: Amortization (years) | B8: 25 | C8: 25 | D8: 20 | E8: 25
A9: IO Period (months) | B9: 0 | C9: 12 | D9: 0 | E9: 12
A10: Loan Fee % | B10: 0.005 | C10: 0.0075 | D10: 0.01 | E10: 0.0075
A11: DSCR Minimum | B11: 1.35 | C11: 1.35 | D11: 1.5 | E11: 1.35
A12: LTV Maximum | B12: 0.55 | C12: 0.6 | D12: 0.75 | E12: 0.75
A14: ANNUAL CASH FLOW (Steady-State)
A15: Annual Debt Service | B15: 182068.75 | C15: 224774.55 | D15: 231902 | E15: 257668.89
A16: Projected NOI | B16: =Dashboard!$B$8 | C16: =Dashboard!$B$8 | D16: =Dashboard!$B$8 | E16: =Dashboard!$B$8
A17: Cash Flow After Debt Service | B17: =B16-B15 | C17: =C16-C15 | D17: =D16-D15 | E17: =E16-E15
A18: DSCR Achieved | B18: =B16/B15 | C18: =C16/C15 | D18: =D16/D15 | E18: =E16/E15
A19: Debt Yield (NOI / Loan) | B19: =B16/B6 | C19: =C16/C6 | D19: =D16/D6 | E19: =E16/E6
A21: CASH OUT AT CLOSE
A22: Loan Amount | B22: =B6 | C22: =C6 | D22: =D6 | E22: =E6
A23: Less: Existing Debt Payoff | B23: =-Dashboard!$B$12 | C23: =-Dashboard!$B$12 | D23: =-Dashboard!$B$12 | E23: =-Dashboard!$B$12
A24: Less: Loan Fee | B24: =-B22*0.005 | C24: =-C22*0.0075 | D24: =-D22*0.01 | E24: =-E22*0.0075
A25: Less: Doc + 3rd Party Costs (est) | B25: -31000 | C25: -31000 | D25: -31000 | E25: -31000
A26: Net Cash to Owner at Close | B26: =B22+B23+B24+B25 | C26: =C22+C23+C24+C25 | D26: =D22+D23+D24+D25 | E26: =E22+E23+E24+E25
A28: RETURNS
A29: Equity Remaining (Basis - Loan) | B29: =Dashboard!$B$11-B22 | C29: =Dashboard!$B$11-C22 | D29: =Dashboard!$B$11-D22 | E29: =Dashboard!$B$11-E22
A30: Cash-on-Cash Return (Steady-State) | B30: =(B16-B15)/B29 | C30: =(C16-C15)/C29 | D30: =(D16-D15)/D29 | E30: =(E16-E15)/E29
A31: Leverage (Loan / Basis) | B31: =B22/Dashboard!$B$11 | C31: =C22/Dashboard!$B$11 | D31: =D22/Dashboard!$B$11 | E31: =E22/Dashboard!$B$11
A33: NOTES:
A34: - ServisFirst (current): max loan calculated as binding minimum of 75% LTV (at 6% cap) and 1.50x DSCR / 6.50% / 20-yr
A35: - ServisFirst (negotiated): assumes ServisFirst gives on rate (-25 bps), amort (+5 yrs), and DSCR floor (-15 bps)
A36: - Cash flow analysis is steady-state (post-IO if applicable). Year 1 may differ for Ben Option 2 due to 12-month IO.
A37: - All scenarios assume current pro forma NOI; adjust on Dashboard tab to test sensitivities.

Sheet Concession Levers
A1: Concession Levers - What Each Concession is Worth
A2: Quantifies how much additional loan capacity each lender concession unlocks
A4: BEN / MBT - OPTION 2 CONCESSION ANALYSIS
A5: Base case: $2.8M / 6.40% / 25-yr / 1.35x DSCR / 60% LTV
A7: Concession | B7: Change | C7: New Max Loan | D7: vs Base $2.8M | E7: $ Value | F7: % Move
A8: BASE CASE | B8: - | C8: 3209762.3 | D8: 0 | E8: - | F8: -
A9: Lower DSCR floor to 1.25x | B9: 1.35x to 1.25x | C9: 3466543.3 | D9: 256780.99 | E9: 256780.99 | F9: 0.08
A10: Lower DSCR floor to 1.20x | B10: 1.35x to 1.20x | C10: 3478530 | D10: 268767.65 | E10: 268767.65 | F10: 0.08373444
A11: Extend amort to 30 years | B11: 25 to 30 yr | C11: 3432806.5 | D11: 223044.14 | E11: 223044.14 | F11: 0.069489299
A12: Lower rate by 25 bps | B12: 6.40% to 6.15% | C12: 3285746.6 | D12: 75984.216 | E12: 75984.216 | F12: 0.023672848
A13: Higher LTV cap to 65% | B13: 60% to 65% | C13: 3209762.3 | D13: 0 | E13: 0 | F13: 0
A14: Higher LTV cap to 70% | B14: 60% to 70% | C14: 3209762.3 | D14: 0 | E14: 0 | F14: 0
A15: Use 5.5% cap rate (vs 6%) | B15: Cap rate 6% to 5.5% | C15: 3209762.3 | D15: 0 | E15: 0 | F15: 0
A16: Combo: 1.25x DSCR + 65% LTV + 30-yr | B16: All concessions | C16: 3707431 | D16: 497668.66 | E16: 497668.66 | F16: 0.15504844
A19: SERVISFIRST CONCESSION ANALYSIS
A20: Base case: 6.50% / 20-yr / 1.50x DSCR / 75% LTV
A22: Concession | B22: Change | C22: New Max Loan | D22: vs Base | E22: $ Value | F22: % Move
A23: BASE CASE | B23: - | C23: 2591988.1 | D23: 0 | E23: - | F23: -
A24: Extend amort to 25 years | B24: 20 to 25 yr | C24: 2862109.3 | D24: 270121.19 | E24: 270121.19 | F24: 0.1042139
A25: Extend amort to 30 years | B25: 20 to 30 yr | C25: 3057450.5 | D25: 465462.39 | E25: 465462.39 | F25: 0.17957737
A26: Lower DSCR floor to 1.35x | B26: 1.50x to 1.35x | C26: 2879986.7 | D26: 287998.67 | E26: 287998.67 | F26: 0.11111111
A27: Lower DSCR floor to 1.25x | B27: 1.50x to 1.25x | C27: 3110385.7 | D27: 518397.61 | E27: 518397.61 | F27: 0.2
A28: Lower rate to 6.25% | B28: 6.50% to 6.25% | C28: 2643921.3 | D28: 51933.27 | E28: 51933.27 | F28: 0.020036076
A29: Lower rate to 6.00% | B29: 6.50% to 6.00% | C29: 2697421.7 | D29: 105433.61 | E29: 105433.61 | F29: 0.040676736
A30: Combo: 25-yr + 1.35x | B30: Two concessions | C30: 3180121.4 | D30: 588133.33 | E30: 588133.33 | F30: 0.22690434
A31: Combo: 25-yr + 1.35x + 6.25% | B31: Three concessions | C31: 3255025.6 | D31: 663037.58 | E31: 663037.58 | F31: 0.25580271
A32: Combo: 30-yr + 1.25x + 6.25% | B32: Match Ben Option 2 effectively | C32: 3766372 | D32: 1174383.9 | E32: 1174383.9 | F32: 0.45308229
A35: STRATEGIC CONCLUSIONS
A36: 1. AMORTIZATION extension is the highest-value single concession. Each 5 years of amort adds ~$200K-$300K of capacity.
A37: 2. DSCR floor reduction is second-highest value. Moving from 1.50x to 1.25x adds ~$370K of capacity at ServisFirst's terms.
A38: 3. Rate reductions are third-most valuable. Each 25 bps of rate reduction adds ~$50K-$80K of capacity.
A39: 4. LTV ceiling matters less when DSCR is binding (which it usually is at conservative cap rates).
A40: 5. For ServisFirst to genuinely beat Ben Opt 2, they need to give on amort (25-yr+) AND DSCR floor (1.35x or lower).
A41: 6. For Ben to compete with a hypothetical aggressive ServisFirst offer, he can give on amort (30-yr) and/or LTV (65%).
